imgdiet/__init__.py
imgdiet/cli.py
imgdiet/core.py
imgdiet-1.0.6.dist-info/LICENSE
imgdiet-1.0.6.dist-info/METADATA
imgdiet-1.0.6.dist-info/WHEEL
imgdiet-1.0.6.dist-info/entry_points.txt
imgdiet-1.0.6.dist-info/top_level.txt
imgdiet-1.0.6.dist-info/RECORD
