Metadata-Version: 2.2
Name: imgdiet
Version: 1.0.6
Summary: A Python package for minimizing file size of images with minimal quality loss
Author-email: Yonghye Kwon <developer.0hye@gmail.com>
License: MIT License
Keywords: image,compression,webp,psnr
License-File: LICENSE
Requires-Dist: numpy
Requires-Dist: Pillow
Requires-Dist: tqdm
